sarphase/__init__.py
sarphase/_version.py
sarphase/setup.py
sarphase/sar/__init__.py
sarphase/sar/download.py
sarphase/sar/operators.py
sarphase/utils/__init__.py
sarphase/utils/auxiliary.py
sarphase/utils/plot.py
sarphase-0.0.7.dist-info/LICENSE.txt
sarphase-0.0.7.dist-info/METADATA
sarphase-0.0.7.dist-info/WHEEL
sarphase-0.0.7.dist-info/top_level.txt
sarphase-0.0.7.dist-info/RECORD
